tornado_httpclient_mock-0.2.3.dist-info/DESCRIPTION.rst
tornado_httpclient_mock-0.2.3.dist-info/METADATA
tornado_httpclient_mock-0.2.3.dist-info/RECORD
tornado_httpclient_mock-0.2.3.dist-info/WHEEL
tornado_httpclient_mock-0.2.3.dist-info/metadata.json
tornado_httpclient_mock-0.2.3.dist-info/top_level.txt
tornado_mock/__init__.py
tornado_mock/compat.py
tornado_mock/httpclient.py
